mxbai_rerank/__init__.py
mxbai_rerank/base.py
mxbai_rerank/mxbai_rerank_v1.py
mxbai_rerank/mxbai_rerank_v2.py
mxbai_rerank/utils.py
mxbai_rerank-0.1.6.dist-info/licenses/LICENSE
mxbai_rerank-0.1.6.dist-info/METADATA
mxbai_rerank-0.1.6.dist-info/WHEEL
mxbai_rerank-0.1.6.dist-info/top_level.txt
mxbai_rerank-0.1.6.dist-info/RECORD
