Metadata-Version: 2.4
Name: mxbai-rerank
Version: 0.1.6
Summary: Crispy reranking models from Mixedbread.
Author-email: Mixedbread <support@mixedbread.com>, Julius Lipp <julius@mixedbread.com>, Sean Lee <sean@mixedbread.com>, Aamir Shakir <aamir@mixedbread.com>, Rui Huang <rui@mixedbread.com>
License: 
Project-URL: Homepage, https://mixedbread.com
Project-URL: Documentation, https://mixedbread.com/blog/mxbai-rerank-v2
Project-URL: Repository, https://github.com/mixedbread-ai/mxbai-rerank
Project-URL: Bug Tracker, https://github.com/mixedbread-ai/mxbai-rerank/issues
Keywords: search,reranking,nlp,machine-learning,transformers
Classifier: Development Status :: 5 - Production/Stable
Classifier: Intended Audience :: Developers
Classifier: Intended Audience :: Science/Research
Classifier: License :: OSI Approved :: Apache Software License
Classifier: Programming Language :: Python :: 3
Classifier: Programming Language :: Python :: 3.9
Classifier: Programming Language :: Python :: 3.10
Classifier: Programming Language :: Python :: 3.11
Classifier: Topic :: Scientific/Engineering :: Artificial Intelligence
Requires-Python: >=3.9
License-File: LICENSE
Requires-Dist: transformers>=4.49.0
Requires-Dist: torch>=2.0.0
Requires-Dist: numpy>=1
Requires-Dist: batched>=0.1.4
Requires-Dist: tqdm>=4.67.1
Requires-Dist: accelerate>=1.5.1
Provides-Extra: dev
Requires-Dist: ruff>=0.9.10; extra == "dev"
Requires-Dist: pip>=24.0; extra == "dev"
Requires-Dist: pytest>=8.0.0; extra == "dev"
Requires-Dist: pytest-cov>=4.1.0; extra == "dev"
Requires-Dist: pytest-mock>=3.12.0; extra == "dev"
Requires-Dist: pre-commit>=3.6.0; extra == "dev"
Dynamic: license-file
